pyMEAL/__init__.py
pyMEAL/basics.py
pyMEAL/builder_block.py
pyMEAL/encoder_concatenation.py
pyMEAL/fusion_layer.py
pyMEAL/plotting.py
pyMEAL/traditional_augmentation.py
pyMEAL/utils.py
pyMEAL/without_augmentation.py
pymeal-1.0.2.dist-info/licenses/LICENSE
pymeal-1.0.2.dist-info/METADATA
pymeal-1.0.2.dist-info/WHEEL
pymeal-1.0.2.dist-info/top_level.txt
pymeal-1.0.2.dist-info/RECORD
