Metadata-Version: 2.4
Name: pyMEAL
Version: 1.0.2
Summary: pyMEAL: Multi-Encoder-Augmentation-Aware-Learning
Home-page: https://github.com/ai-vbrain/pyMEAL
Author: The Hong Kong Center for Cerebrocardivascular Health Engineering (COCHE)
Author-email: amaradesa@connect.ust.hk
Project-URL: Source Code, https://github.com/ai-vbrain/pyMEAL
Project-URL: Bug Tracker, https://github.com/ai-vbrain/pyMEAL/issues
Classifier: Programming Language :: Python :: 3
Classifier: Programming Language :: Python :: 3.4
Classifier: Programming Language :: Python :: 3.5
Classifier: Programming Language :: Python :: 3.6
Classifier: Programming Language :: Python :: 3.7
Classifier: Programming Language :: Python :: 3.8
Classifier: License :: OSI Approved :: MIT License
Classifier: Operating System :: OS Independent
Requires-Python: >=3
License-File: LICENSE
Requires-Dist: tensorflow==2.9.0
Requires-Dist: matplotlib==3.9.2
Requires-Dist: SimpleITK==2.4.0
Requires-Dist: scipy==1.13.1
Requires-Dist: antspyx==0.5.4
Requires-Dist: numpy==1.23.5
Requires-Dist: imageio==2.36.0
Requires-Dist: nibabel==5.3.2
Requires-Dist: pillow==11.0.0
Dynamic: author
Dynamic: author-email
Dynamic: classifier
Dynamic: description
Dynamic: description-content-type
Dynamic: home-page
Dynamic: license-file
Dynamic: project-url
Dynamic: requires-dist
Dynamic: requires-python
Dynamic: summary
